pemja_utils.cpython-313-darwin.so
pemja_core.cpython-313-darwin.so
pemja/version.py
pemja/redirect_stream.py
pemja/__init__.py
pemja/import_sentinel.py
pemja/display_patch.py
pemja/timeout_handler.py
pemjax-0.2.3.dist-info/RECORD
pemjax-0.2.3.dist-info/WHEEL
pemjax-0.2.3.dist-info/top_level.txt
pemjax-0.2.3.dist-info/METADATA
pemjax-0.2.3.dist-info/licenses/LICENSE
